zwtk/__init__.py
zwtk/__version__.py
zwtk/comm.py
zwtk/config.py
zwtk/dlso.py
zwtk/fileutils.py
zwtk/geoutils.py
zwtk/mprocessing.py
zwtk/mthreading.py
zwtk/osutils.py
zwtk/rand.py
zwtk/reutils.py
zwtk/setting.py
zwtk/textutils.py
zwtk/urlutils.py
zwtk/usn.py
zwtk/zwsqlite.py
zwtk-1.0.4.dist-info/LICENSE
zwtk-1.0.4.dist-info/METADATA
zwtk-1.0.4.dist-info/WHEEL
zwtk-1.0.4.dist-info/top_level.txt
zwtk-1.0.4.dist-info/RECORD
